<?xml version="1.0" encoding="UTF-8"?>
<LanguageData>
  
  <!-- EN: install dreamcatcher -->
  <AC_InstallDreamcatcher.label>implantar atrapasueños</AC_InstallDreamcatcher.label>
  <!-- EN: Install a dreamcatcher. -->
  <AC_InstallDreamcatcher.description>Implantar un atrapasueños.</AC_InstallDreamcatcher.description>
  <!-- EN: Installing dreamcatcher. -->
  <AC_InstallDreamcatcher.jobString>Implantando atrapasueños.</AC_InstallDreamcatcher.jobString>
  
  <!-- EN: install mental fuse -->
  <AC_InstallMentalFuse.label>implantar fusible mental</AC_InstallMentalFuse.label>
  <!-- EN: Install a mental fuse. -->
  <AC_InstallMentalFuse.description>Implantar un fusible mental.</AC_InstallMentalFuse.description>
  <!-- EN: Installing mental fuse. -->
  <AC_InstallMentalFuse.jobString>Implantando fusible mental.</AC_InstallMentalFuse.jobString>
  
  <!-- EN: install voice synthesizer -->
  <AC_InstallVoiceSynthesizer.label>implantar sintetizador de voz</AC_InstallVoiceSynthesizer.label>
  <!-- EN: Install a voice synthesizer. -->
  <AC_InstallVoiceSynthesizer.description>Implantar un sintetizador de voz.</AC_InstallVoiceSynthesizer.description>
  <!-- EN: Installing voice synthesizer. -->
  <AC_InstallVoiceSynthesizer.jobString>Implantando sintetizador de voz.</AC_InstallVoiceSynthesizer.jobString>
  
  <!-- EN: remove dreamcatcher -->
  <AC_RemoveDreamcatcher.label>eliminar atrapasueños</AC_RemoveDreamcatcher.label>
  <!-- EN: Remove dreamcatcher. -->
  <AC_RemoveDreamcatcher.description>Amputar un miembro corporal.</AC_RemoveDreamcatcher.description>
  <!-- EN: Removing dreamcatcher. -->
  <AC_RemoveDreamcatcher.jobString>Amputando miembro.</AC_RemoveDreamcatcher.jobString>
  
  <!-- EN: remove mental fuse -->
  <AC_RemoveMentalFuse.label>eliminar fusible mental</AC_RemoveMentalFuse.label>
  <!-- EN: Remove mental fuse. -->
  <AC_RemoveMentalFuse.description>Amputar un miembro corporal.</AC_RemoveMentalFuse.description>
  <!-- EN: Removing mental fuse. -->
  <AC_RemoveMentalFuse.jobString>Amputando miembro.</AC_RemoveMentalFuse.jobString>
  
  <!-- EN: remove voice synthesizer -->
  <AC_RemoveVoiceSynthesizer.label>eliminar sintetizador de voz</AC_RemoveVoiceSynthesizer.label>
  <!-- EN: Remove voice synthesizer. -->
  <AC_RemoveVoiceSynthesizer.description>Amputar un miembro corporal.</AC_RemoveVoiceSynthesizer.description>
  <!-- EN: Removing voice synthesizer. -->
  <AC_RemoveVoiceSynthesizer.jobString>Amputando miembro.</AC_RemoveVoiceSynthesizer.jobString>
  
</LanguageData>