<?xml version='1.0' encoding='utf-8'?>
<LanguageData>
  <UV_OverclockBroadcast.comps.CompUsableImplant.useLabel>Implantar subenlace</UV_OverclockBroadcast.comps.CompUsableImplant.useLabel>
  <UV_OverclockBroadcast.description>Un chip que permite al mecanizador mejorar drásticamente los enlaces de control, proporcionando suministro de energía remoto y computación distribuida. Todos los mecanoides aliados en el mismo mapa que el mecanizador obtendrán una mayor velocidad de movimiento y eficiencia de trabajo.</UV_OverclockBroadcast.description>
  <UV_OverclockBroadcast.label>transmisión de sobreaceleración</UV_OverclockBroadcast.label>
  <UV_QuantumCoherenceChip.comps.CompUsable.useLabel>Usar {0_label}</UV_QuantumCoherenceChip.comps.CompUsable.useLabel>
  <UV_QuantumCoherenceChip.description>Un componente mecánico de coherencia cuántica en miniatura utilizado para reutilizar restos de mecanoides. Anula los protocolos hostiles del objetivo y reescribe su firma de hardware para alinearse con tu facción.</UV_QuantumCoherenceChip.description>
  <UV_QuantumCoherenceChip.label>chip de coherencia cuántica</UV_QuantumCoherenceChip.label>
</LanguageData>
