<?xml version='1.0' encoding='utf-8'?>
<LanguageData>
  <VQED_AncientKinoProjector.description>Una antigua unidad de proyección posicionada para su uso con una pantalla a juego. Funciona cuando tiene energía, pero solo si apunta a la pantalla de cine.</VQED_AncientKinoProjector.description>
  <VQED_AncientKinoProjector.label>proyector de cine antiguo</VQED_AncientKinoProjector.label>
  <VQED_AncientKinoScreen.description>Una pantalla masiva del viejo mundo utilizada antaño para el visionado comunitario. Las imágenes granuladas cobran vida solo cuando se emparejan con un proyector de cine en funcionamiento. Sigue siendo extrañamente cautivadora a pesar de la estática y la distorsión.</VQED_AncientKinoScreen.description>
  <VQED_AncientKinoScreen.label>pantalla de cine antigua</VQED_AncientKinoScreen.label>
</LanguageData>
