<?xml version="1.0" encoding="UTF-8"?>
<LanguageData>
  
  <!-- EN: blood belcher -->
  <AM_Gun_BloodBelcher.label>escupidor de sangre</AM_Gun_BloodBelcher.label>
  <!-- EN: A fearsome weapon that harnesses the power of boiling, acidic blood. When activated, the Blood Belcher propels a high-pressure stream of acidic hemogen towards its target. -->
  <AM_Gun_BloodBelcher.description>Un arma temible que aprovecha el poder de la sangre ácida hirviente. Al activarse, el escupidor de sangre propulsa un chorro de hemogenina ácida a alta presión hacia su objetivo.</AM_Gun_BloodBelcher.description>
  <!-- EN: barrel -->
  <AM_Gun_BloodBelcher.tools.barrel.label>cañón</AM_Gun_BloodBelcher.tools.barrel.label>
  
  <!-- EN: boiling hemogen -->
  <AM_Bullet_BloodBelcher.label>hemogenina hirviente</AM_Bullet_BloodBelcher.label>
  
</LanguageData>
