<?xml version='1.0' encoding='utf-8'?>
<LanguageData>
  <MU_CommandCancelUpgrading>Cancelar proceso</MU_CommandCancelUpgrading>
  <MU_CommandCancelUpgrading_Desc>Cancela el proceso de mejora. El mecanoide contenido será expulsado.</MU_CommandCancelUpgrading_Desc>
  <MU_CommandCancelWaiting>Cancelar mejora</MU_CommandCancelWaiting>
  <MU_CommandCancelWaiting_Desc>Cancela el proceso de mejora. El mecanoide contenido será expulsado.</MU_CommandCancelWaiting_Desc>
  <MU_ForceReload>Forzar recarga...</MU_ForceReload>
  <MU_ForceReload_Desc>Fuerza al mecanoide a recargar una de las mejoras que lo requiera.</MU_ForceReload_Desc>
  <MU_InsertMech>Insertar mecanoide</MU_InsertMech>
  <MU_InsertMech_Desc>Inserta un mecanoide en el mejorador de mecanoides. Después de la inserción, el mecanizador debería iniciar el proceso de mejora.</MU_InsertMech_Desc>
  <MU_MechBooster_Desc>Cambia el impulsor de mecanoide a otro modo.</MU_MechBooster_Desc>
  <MU_MechBooster_Label>Cambiar impulsor de mecanoide</MU_MechBooster_Label>
</LanguageData>
