<?xml version='1.0' encoding='utf-8'?>
<LanguageData>
  <VFEI2_Chemfuel>Plenitud de quimbustible:</VFEI2_Chemfuel>
  <VFEI2_Chitin>Mudando quitina en:</VFEI2_Chitin>
  <VFEI2_PatriarchNotTameable>El Patriarca no se puede domesticar</VFEI2_PatriarchNotTameable>
  <VFEI2_RoyalInsectJelly>Plenitud de jalea de insecto real:</VFEI2_RoyalInsectJelly>
  <VFEI_AlertInsectWaveIncoming>{0} entrante</VFEI_AlertInsectWaveIncoming>
  <VFEI_AlertInsectWaveIncomingDesc>Alertado por tu golpeador, un {0} hostil con un ejército de insectoides está cavando su camino hacia la superficie. Llegarán en unas pocas horas.</VFEI_AlertInsectWaveIncomingDesc>
  <VFEI_AlreadyActivated>ya activado</VFEI_AlreadyActivated>
  <VFEI_BaseArtificalInsectCount>Recuento base de insectos de colmena artificial</VFEI_BaseArtificalInsectCount>
  <VFEI_BaseTimeBetweenHanHordeWaves>Tiempo base entre oleadas del modo Han Horda</VFEI_BaseTimeBetweenHanHordeWaves>
  <VFEI_BurrowCollapsed>La madriguera de insectoides se ha vuelto inestable y se ha derrumbado.</VFEI_BurrowCollapsed>
  <VFEI_BurrowWaves>{0} oleadas de insectoides de {1}</VFEI_BurrowWaves>
  <VFEI_CannotPlaceCloseToOtherBasicHive>No se puede colocar cerca de otra colmena básica artificial</VFEI_CannotPlaceCloseToOtherBasicHive>
  <VFEI_CannotPlaceCloseToOtherCreeper>No se puede colocar cerca de otra trepadora.</VFEI_CannotPlaceCloseToOtherCreeper>
  <VFEI_CannotPlaceCloseToOtherJellyFarm>No se puede colocar cerca de otra granja de jalea.</VFEI_CannotPlaceCloseToOtherJellyFarm>
  <VFEI_CannotUseRoofed>El lanzador está en un área techada.</VFEI_CannotUseRoofed>
  <VFEI_CargoPodsSentForCompletingWave>Se han enviado cápsulas de carga por completar la oleada.</VFEI_CargoPodsSentForCompletingWave>
  <VFEI_ChooseInsectoidColor>Elegir color de insectoide {0}</VFEI_ChooseInsectoidColor>
  <VFEI_CocoonInsectSpawnIn>{0} antes de la aparición del insecto.</VFEI_CocoonInsectSpawnIn>
  <VFEI_CreatingCocoon>{0} para crear capullo</VFEI_CreatingCocoon>
  <VFEI_CreeperSpawnSpeed>Velocidad de generación de trepadora</VFEI_CreeperSpawnSpeed>
  <VFEI_DefenderDesc>Los insectoides defensores protegen vigilantemente su colmena atacando a cualquier entidad hostil que entre en un radio designado.</VFEI_DefenderDesc>
  <VFEI_DueForMaintenance>Mantenimiento necesario. {0} hasta que comience a deteriorarse.</VFEI_DueForMaintenance>
  <VFEI_EnemiesComing>Enemigos en camino:</VFEI_EnemiesComing>
  <VFEI_HiveArea>Área de colmena</VFEI_HiveArea>
  <VFEI_HiveAreaClear>Borrar área de colmena</VFEI_HiveAreaClear>
  <VFEI_HiveAreaClearDesc>Elimina un área de colmena. Tus insectoides ya no trabajarán, buscarán presas ni atacarán objetivos hostiles aquí.</VFEI_HiveAreaClearDesc>
  <VFEI_HiveAreaExpand>Expandir área de colmena</VFEI_HiveAreaExpand>
  <VFEI_HiveAreaExpandDesc>Crea un área de colmena donde tus colmenas de insectoides trabajarán, buscarán presas y atacarán objetivos hostiles. Tus insectoides no abandonarán el área de la colmena.</VFEI_HiveAreaExpandDesc>
  <VFEI_HiveCannotBeUpgradedMore>No se puede mejorar: se alcanzó el tamaño máximo de la {0}.</VFEI_HiveCannotBeUpgradedMore>
  <VFEI_HiveCloseProximityWarning>Construir colmenas artificiales muy cerca unas de otras aumentará su necesidad de mantenimiento.</VFEI_HiveCloseProximityWarning>
  <VFEI_HunterDesc>Los insectoides cazadores buscan y cazan proactivamente la vida silvestre cerca de su colmena, trayendo y almacenando las presas para el consumo comunitario.</VFEI_HunterDesc>
  <VFEI_Infestation>Infestación</VFEI_Infestation>
  <VFEI_InfestationHasSpread>Misión fallida: {0}</VFEI_InfestationHasSpread>
  <VFEI_InfestationHasSpreadDesc>La colmena de insectoides se ha extendido. La misión {0} ha terminado.</VFEI_InfestationHasSpreadDesc>
  <VFEI_InfestationTooltip>Si esta casilla está bajo los efectos de una infestación de insectoides.\n\nLas áreas alrededor de las colmenas de insectoides a menudo están repletas de insectos, con varias estructuras construidas por insectos que afectan el medio ambiente. Es mucho más probable que ocurran infestaciones, y los grupos de viaje pueden encontrar insectoides errantes.</VFEI_InfestationTooltip>
  <VFEI_InsectSummonWarning>Activar el {0} invocará a los siguientes insectos hostiles:\n\n{PAWNS}\n\n¿Estás listo para luchar?</VFEI_InsectSummonWarning>
  <VFEI_InsectTerritoryScale>Área infestada</VFEI_InsectTerritoryScale>
  <VFEI_InsectoidWillBeSpawnedIn>{0} aparecerá en: {1}</VFEI_InsectoidWillBeSpawnedIn>
  <VFEI_Insectoids>Insectoides</VFEI_Insectoids>
  <VFEI_JellyFarmProductionAmount>Cantidad de producción de granja de jalea</VFEI_JellyFarmProductionAmount>
  <VFEI_LarvaeTimeSpawn>{0} antes de la próxima aparición de enjambradores.</VFEI_LarvaeTimeSpawn>
  <VFEI_LetterInsectWaveArrived>Un líder insectoide de {0} ha venido a erradicarte, junto con escoltas.\n\nEl grupo de asalto está compuesto por los siguientes insectos:\n\n{1}</VFEI_LetterInsectWaveArrived>
  <VFEI_LetterInsectWaveSummoned>Atraído por las vibraciones de tu golpeador, un líder insectoide de {0} emergerá del suelo pronto. Prepárate.</VFEI_LetterInsectWaveSummoned>
  <VFEI_LetterLabelInsectWaveArrived>{0} llegó</VFEI_LetterLabelInsectWaveArrived>
  <VFEI_LetterLabelInsectWaveSummoned>{0} invocado</VFEI_LetterLabelInsectWaveSummoned>
  <VFEI_MaintainedByHivenode>Mantenido por nodo de colmena</VFEI_MaintainedByHivenode>
  <VFEI_MaintenanceLossSpeed>Velocidad de pérdida de mantenimiento: {0}</VFEI_MaintenanceLossSpeed>
  <VFEI_MinHiveStabilityDistance>Penalización por distancia de colmena artificial cercana</VFEI_MinHiveStabilityDistance>
  <VFEI_ModNameForSettings>VFE - Insectoids 2</VFEI_ModNameForSettings>
  <VFEI_NeedsToBeMaintainedIn>Mantenimiento necesario en {0}</VFEI_NeedsToBeMaintainedIn>
  <VFEI_NextInsectBurrowing>Próximo insectoide cavando en: {0}</VFEI_NextInsectBurrowing>
  <VFEI_NoMoreSpawningAllowed>La reina está descansando.</VFEI_NoMoreSpawningAllowed>
  <VFEI_NotForPlayers>Este Patriarca está bajo el control del jugador y, por lo tanto, no tiene conexión con una colmena salvaje</VFEI_NotForPlayers>
  <VFEI_OnCooldown>estará disponible en {0}</VFEI_OnCooldown>
  <VFEI_OtherThumperIsActive>otro golpeador está activo</VFEI_OtherThumperIsActive>
  <VFEI_PherocoreCanBeUsedOnHive>{0} solo se puede usar en una {1}.</VFEI_PherocoreCanBeUsedOnHive>
  <VFEI_Present>Presente</VFEI_Present>
  <VFEI_RequiresFloor>{0_label} necesita {1} debajo.</VFEI_RequiresFloor>
  <VFEI_ResearchUnlockedForCompletingWave>{0} se ha desbloqueado por completar la oleada.</VFEI_ResearchUnlockedForCompletingWave>
  <VFEI_SettleWarning>Esta casilla está cerca de una colmena de insectoides, por lo que habrá una influencia de insectoides siempre presente en ella. Las infestaciones ocurrirán cada {0} días. Es mucho más probable que ocurran grandes infestaciones, y pueden ocurrir en cualquier lugar, no solo en áreas oscuras. Las megaarañas, los espelópodos y los megaescarabajos deambulan libremente, y las caravanas que viajan pueden tener que defenderse de enjambres de insectoides.</VFEI_SettleWarning>
  <VFEI_SpawningStoppedMaxCapacity>Generación detenida: capacidad máxima alcanzada.</VFEI_SpawningStoppedMaxCapacity>
  <VFEI_StabilityHiveMaintenancePenalty>Penalización de mantenimiento por estabilidad de colmena</VFEI_StabilityHiveMaintenancePenalty>
  <VFEI_TendrilmossSpawnSpeed>Velocidad de generación de granja de zarcillos</VFEI_TendrilmossSpawnSpeed>
  <VFEI_TimeUntilThornsRegrow>Tiempo hasta que las espinas vuelvan a crecer: {0}</VFEI_TimeUntilThornsRegrow>
  <VFEI_WaveActivityOverlay>Actividad: {0}.\nMultiplicador de tamaño de oleada: {1}.\nTiempo antes de la oleada: {2}.\nLínea genética elegida: {3}.</VFEI_WaveActivityOverlay>
  <VFEI_WorkerDesc>Los insectoides obreros tienen la tarea de construir y mantener estructuras específicas de insectoides, así como realizar tareas esenciales de transporte y minería.</VFEI_WorkerDesc>
</LanguageData>
