<?xml version="1.0" encoding="UTF-8"?>
<LanguageData>
  
  <!-- EN: sanguine -->
  <AS_SanguinePassion.label>sanguínea</AS_SanguinePassion.label>
  <!-- EN: This passion is fueled by vitality. They learn faster when their hemogen levels are high (above 50%). -->
  <AS_SanguinePassion.description>Esta pasión se alimenta de la vitalidad. Aprenden más rápido cuando sus niveles de hemógeno son altos (por encima del 50%).</AS_SanguinePassion.description>
  
  <!-- EN: sanguine (active) -->
  <AS_SanguinePassion_Active.label>sanguínea (activa)</AS_SanguinePassion_Active.label>
  <!-- EN: This passion is fueled by vitality. They learn faster when their hemogen levels are high. Hemogen level is above 50% now. -->
  <AS_SanguinePassion_Active.description>Esta pasión se alimenta de la vitalidad. Aprenden más rápido cuando sus niveles de hemógeno son altos. El nivel de hemógeno está por encima del 50% ahora.</AS_SanguinePassion_Active.description>
  
  <!-- EN: toxic -->
  <AS_ToxicPassion.label>tóxica</AS_ToxicPassion.label>
  <!-- EN: This passion thrives in filth and decay. They will learn faster when surrounded by pollution. -->
  <AS_ToxicPassion.description>Esta pasión prospera en la inmundicia y la decadencia. Aprenderán más rápido cuando estén rodeados de contaminación.</AS_ToxicPassion.description>
  
  <!-- EN: toxic (active) -->
  <AS_ToxicPassion_Active.label>tóxica (activa)</AS_ToxicPassion_Active.label>
  <!-- EN: This passion thrives in filth and decay. They will learn faster when surrounded by pollution. This person is in polluted terrain right now. -->
  <AS_ToxicPassion_Active.description>Esta pasión prospera en la inmundicia y la decadencia. Aprenderán más rápido cuando estén rodeados de contaminación. Esta persona está en terreno contaminado ahora mismo.</AS_ToxicPassion_Active.description>
  
</LanguageData>