<?xml version="1.0" encoding="UTF-8"?>
<LanguageData>
  
  <!-- EN: Growing dandelions -->
  <FloralHydroponic_Dandelions.label>Cultivando dientes de león</FloralHydroponic_Dandelions.label>
  <!-- EN: Grow dandelions. -->
  <FloralHydroponic_Dandelions.description>Cultivar dientes de león.</FloralHydroponic_Dandelions.description>
  <!-- EN: Grow dandelions -->
  <FloralHydroponic_Dandelions.labelOverride>Cultivar dientes de león</FloralHydroponic_Dandelions.labelOverride>
  
  <!-- EN: Growing daylilies -->
  <FloralHydroponic_Daylily.label>Cultivando lirios de día</FloralHydroponic_Daylily.label>
  <!-- EN: Grow daylilies. -->
  <FloralHydroponic_Daylily.description>Cultivar lirios de día.</FloralHydroponic_Daylily.description>
  <!-- EN: Grow daylilies -->
  <FloralHydroponic_Daylily.labelOverride>Cultivar lirios de día</FloralHydroponic_Daylily.labelOverride>
  
  <!-- EN: Growing roses -->
  <FloralHydroponic_Rose.label>Cultivando rosas</FloralHydroponic_Rose.label>
  <!-- EN: Grow roses. -->
  <FloralHydroponic_Rose.description>Cultivar rosas.</FloralHydroponic_Rose.description>
  <!-- EN: Grow roses -->
  <FloralHydroponic_Rose.labelOverride>Cultivar rosas</FloralHydroponic_Rose.labelOverride>
  
</LanguageData>