<?xml version='1.0' encoding='utf-8'?>
<LanguageData>
  <VREA_ButcherCorpseAndroid.description>Tritura un androide muerto para intentar recuperar material utilizable.</VREA_ButcherCorpseAndroid.description>
  <VREA_ButcherCorpseAndroid.jobString>Triturando androide.</VREA_ButcherCorpseAndroid.jobString>
  <VREA_ButcherCorpseAndroid.label>triturar androide</VREA_ButcherCorpseAndroid.label>
  <VREA_RemoveArtificialPart.description>Quita una parte corporal artificial.</VREA_RemoveArtificialPart.description>
  <VREA_RemoveArtificialPart.jobString>Quitando parte del cuerpo artificial.</VREA_RemoveArtificialPart.jobString>
  <VREA_RemoveArtificialPart.label>eliminar componente</VREA_RemoveArtificialPart.label>
</LanguageData>
