<?xml version='1.0' encoding='utf-8'?>
<LanguageData>
  <VFEP_PlayerPirate.description>Una pequeña cala pirata.</VFEP_PlayerPirate.description>
  <VFEP_PlayerPirate.label>Nueva Cala</VFEP_PlayerPirate.label>
  <VFEP_PlayerPirate.leaderTitle>líder</VFEP_PlayerPirate.leaderTitle>
  <VFEP_PlayerPirate.messageDefendersAttacking>{0} de {1} están atacando tu {2}.</VFEP_PlayerPirate.messageDefendersAttacking>
  <VFEP_PlayerPirate.pawnSingular>pirata</VFEP_PlayerPirate.pawnSingular>
  <VFEP_PlayerPirate.pawnsPlural>piratas</VFEP_PlayerPirate.pawnsPlural>
</LanguageData>
