<?xml version="1.0" encoding="UTF-8"?>
<LanguageData>
  
  <!-- EN:
    <li>lastOrNot(nobleCount==1)-></li>
    <li>lastOrNot(nobleCount>=2)->last</li>
    <li>lodgersLabelSingularOrPlural(nobleCount==1)->[lodgersLabel]</li>
    <li>lodgersLabelSingularOrPlural(nobleCount>=2)->[lodgersLabelPlural]</li>
    <li>decidedToLeave->Are leaving immediately, and will not remember this event fondly!</li>
    <li>oneOfThe->one of the nobles visting for the parade</li>
    <li>questOver->The quest '[resolvedQuestName]' is over.</li>
    <li>CeremonyFailedLetterLabel->Parade failed</li>
    <li>CeremonyFailedLetterText->[asker_nameFull] is disappointed by your failure to make for an enjoyable Parade. [asker_pronoun] is leaving with [asker_possessive] guests</li>
    <li>CeremonyTimeoutLetterLabel->Parade failed</li>
    <li>CeremonyTimeoutLetterText->[asker_nameFull] has grown tired of waiting for you to start the Parade. [asker_pronoun] is leaving with [asker_possessive] guests.</li>
    <li>letterIntroArrested->You arrested {SUBJECT_definite}, [oneOfThe].</li>
    <li>lodgerArrestedLeaveMapLetterLabel->[lodgersLabel] arrested</li>
    <li>lodgerArrestedLeaveMapLetterText->[letterIntroArrested]\n\n[decidedToLeave]</li>
    <li>letterIntroDeath->{SUBJECT_definite}, [oneOfThe] has died.</li>
    <li>lodgerDiedLeaveMapLetterLabel->[lodgersLabel] died: Departure</li>
    <li>lodgerDiedLeaveMapLetterText->[letterIntroDeath]\n\n[decidedToLeave]</li>
    <li>letterIntroViolated->{SUBJECT_definite}, [oneOfThe], was violated by surgery.</li>
    <li>lodgerSurgeryVioLeaveMapLetterLabel->[lodgersLabel] Surgery: Departure</li>
    <li>lodgerSurgeryVioLeaveMapLetterText->[letterIntroViolated]\n\n[decidedToLeave]</li>
    <li>letterIntroKidnapped->{SUBJECT_definite}, [oneOfThe], was kidnapped.</li>
    <li>lodgerKidnappedLeaveMapLetterLabel->[lodgersLabel] Kidnapped: Departure</li>
    <li>lodgerKidnappedLeaveMapLetterText->[letterIntroKidnapped]\n\n[decidedToLeave]</li>
    <li>letterIntroBanished->{SUBJECT_definite}, [oneOfThe], was banished.</li>
    <li>lodgerBanishedLeaveMapLetterLabel->[lodgersLabel] Banished: Departure</li>
    <li>lodgerBanishedLeaveMapLetterText->[letterIntroBanished]\n\n[decidedToLeave]</li>
    <li>letterIntroPsychicRitualTarget->{SUBJECT_definite}, [oneOfThe], was the target of a psychic ritual.</li>
    <li>lodgerPsychicRitualTargetLabel->[lodgersLabel] Psychic Ritual: Departure</li>
    <li>lodgerPsychicRitualTargetText->[letterIntroPsychicRitualTarget]\n\n[decidedToLeave]</li>
    <li>ShuttleDestroyedIntro->{SUBJECT_definite}, has been destroyed</li>
    <li>ShuttleDestroyedLabel->Shuttle destroyed: Parade Failed</li>
    <li>ShuttleDestroyedText->[ShuttleDestroyedIntro]\n\n[decidedToLeave]</li>
    <li>raidArrivedLetterLabel->Deserter assasination attempt</li>
    <li>raidArrivedLetterText->A group of deserters have arrived to attempt to disrupt the parade and assasinate the [stellarch_nameFull]\n\nThe parade must not be interrupted for any reason!</li>
    <li>ParadeSuccessLetterLetterLabel->Parade Success</li>
    <li>ParadeSuccessLetterText->The shuttle is ready to depart with all those ascending with [stellarch_nameFull]. It will depart upon your command!</li>
  -->
  <VFEE_Parade.questContentRules.rulesStrings>
    <li>lastOrNot(nobleCount==1)-></li>
    <li>lastOrNot(nobleCount>=2)->último</li>
    <li>lodgersLabelSingularOrPlural(nobleCount==1)->[lodgersLabel]</li>
    <li>lodgersLabelSingularOrPlural(nobleCount>=2)->[lodgersLabelPlural]</li>
    <li>decidedToLeave->¡Se van inmediatamente y no recordarán este evento con cariño!</li>
    <li>oneOfThe->uno de los nobles que visitan para el desfile</li>
    <li>questOver->La misión '[resolvedQuestName]' ha terminado.</li>
    <li>CeremonyFailedLetterLabel->Desfile fallido</li>
    <li>CeremonyFailedLetterText->[asker_nameFull] está decepcionado por tu fracaso en hacer un desfile agradable. [asker_pronoun] se va con sus invitados</li>
    <li>CeremonyTimeoutLetterLabel->Desfile fallido</li>
    <li>CeremonyTimeoutLetterText->[asker_nameFull] se ha cansado de esperar a que comiences el desfile. [asker_pronoun] se va con sus invitados.</li>
    <li>letterIntroArrested->Arrestaste a {SUBJECT_definite}, [oneOfThe].</li>
    <li>lodgerArrestedLeaveMapLetterLabel->[lodgersLabel] arrestado</li>
    <li>lodgerArrestedLeaveMapLetterText->[letterIntroArrested]\n\n[decidedToLeave]</li>
    <li>letterIntroDeath->{SUBJECT_definite}, [oneOfThe] ha muerto.</li>
    <li>lodgerDiedLeaveMapLetterLabel->[lodgersLabel] murió: Partida</li>
    <li>lodgerDiedLeaveMapLetterText->[letterIntroDeath]\n\n[decidedToLeave]</li>
    <li>letterIntroViolated->{SUBJECT_definite}, [oneOfThe], fue violado por cirugía.</li>
    <li>lodgerSurgeryVioLeaveMapLetterLabel->[lodgersLabel] Cirugía: Partida</li>
    <li>lodgerSurgeryVioLeaveMapLetterText->[letterIntroViolated]\n\n[decidedToLeave]</li>
    <li>letterIntroKidnapped->{SUBJECT_definite}, [oneOfThe], fue secuestrado.</li>
    <li>lodgerKidnappedLeaveMapLetterLabel->[lodgersLabel] Secuestrado: Partida</li>
    <li>lodgerKidnappedLeaveMapLetterText->[letterIntroKidnapped]\n\n[decidedToLeave]</li>
    <li>letterIntroBanished->{SUBJECT_definite}, [oneOfThe], fue desterrado.</li>
    <li>lodgerBanishedLeaveMapLetterLabel->[lodgersLabel] Desterrado: Partida</li>
    <li>lodgerBanishedLeaveMapLetterText->[letterIntroBanished]\n\n[decidedToLeave]</li>
    <li>letterIntroPsychicRitualTarget->{SUBJECT_definite}, [oneOfThe], fue el objetivo de un ritual psíquico.</li>
    <li>lodgerPsychicRitualTargetLabel->[lodgersLabel] Ritual psíquico: Partida</li>
    <li>lodgerPsychicRitualTargetText->[letterIntroPsychicRitualTarget]\n\n[decidedToLeave]</li>
    <li>ShuttleDestroyedIntro->{SUBJECT_definite}, ha sido destruido</li>
    <li>ShuttleDestroyedLabel->Transbordador destruido: Desfile fallido</li>
    <li>ShuttleDestroyedText->[ShuttleDestroyedIntro]\n\n[decidedToLeave]</li>
    <li>raidArrivedLetterLabel->Intento de asesinato de desertores</li>
    <li>raidArrivedLetterText->Un grupo de desertores ha llegado para intentar interrumpir el desfile y asesinar al [stellarch_nameFull]\n\n¡El desfile no debe ser interrumpido por ninguna razón!</li>
    <li>ParadeSuccessLetterLetterLabel->Éxito del desfile</li>
    <li>ParadeSuccessLetterText->El transbordador está listo para partir con todos aquellos que ascienden con el [stellarch_nameFull]. ¡Partirá a tu orden!</li>
  </VFEE_Parade.questContentRules.rulesStrings>
  <!-- EN:
    <li>lodgersLabel->noble</li>
    <li>lodgersLabelPlural->nobles</li>
    <li>lodgersDef(nobleCount==1)->[lodgers0_nameDef]</li>
    <li>lodgersDef(nobleCount>=2)->the [lodgersLabelPlural]</li>
    <li>theirHisHer(nobleCount==1)->[lodgers0_possessive]</li>
    <li>theirHisHer(nobleCount>=2)->their</li>
    <li>lodgersPronoun(nobleCount==1)->[lodgers0_pronoun]</li>
    <li>lodgersPronoun(nobleCount>=2)->they</li>
    <li>lodgersWasWere(nobleCount==1)->was</li>
    <li>lodgersWasWere(nobleCount>=2)->were</li>
    <li>appreciateAppreciates(nobleCount==1)->appreciates</li>
    <li>appreciateAppreciates(nobleCount>=2)->appreciate</li>
    <li>questDescription->[stellarch_nameFull] has reached the peak of what they can achieve from a surface of the rim world. In order to progress further in the grand hierarchy and become the right hand of Emperor [emperor_nameFull], [stellarch_nameFull] needs to partake in a traditional ascension parade, after which they will depart on a shuttle and join the Emperor.\nParade of this magnitude is bound to draw the attention of deserters.\nOnce you accept this quest, you will have 5 days to prepare for the parade. Consider improving your defenses and working out contingency plans, as it is difficult to say which way the parade will move. At all times you will have to keep the parade safe from harm.\nKeep an eye on any rivals or enemies of [stellarch_nameFull], as they might decide it’s a good time to make a move and claim the power for themselves.\nThe shuttle will arrive bringing the highest ranking nobility to the parade. You will be responsible for providing the security for the event. After the parade starts, it will slowly move through the map for 12 hours, after which everyone, including [stellarch_nameFull], will board the shuttle and depart.\n\n\n\n			</li>
  -->
  <VFEE_Parade.questDescriptionAndNameRules.rulesStrings>
    <li>lodgersLabel->noble</li>
    <li>lodgersLabelPlural->nobles</li>
    <li>lodgersDef(nobleCount==1)->[lodgers0_nameDef]</li>
    <li>lodgersDef(nobleCount>=2)->los [lodgersLabelPlural]</li>
    <li>theirHisHer(nobleCount==1)->[lodgers0_possessive]</li>
    <li>theirHisHer(nobleCount>=2)->su</li>
    <li>lodgersPronoun(nobleCount==1)->[lodgers0_pronoun]</li>
    <li>lodgersPronoun(nobleCount>=2)->ellos</li>
    <li>lodgersWasWere(nobleCount==1)->fue</li>
    <li>lodgersWasWere(nobleCount>=2)->fueron</li>
    <li>appreciateAppreciates(nobleCount==1)->aprecia</li>
    <li>appreciateAppreciates(nobleCount>=2)->aprecian</li>
    <li>questDescription->[stellarch_nameFull] ha alcanzado la cima de lo que puede lograr desde la superficie de un mundo borde. Para progresar más en la gran jerarquía y convertirse en la mano derecha del Emperador [emperor_nameFull], [stellarch_nameFull] necesita participar en un desfile de ascensión tradicional, después del cual partirá en un transbordador y se unirá al Emperador.\nUn desfile de esta magnitud seguramente atraerá la atención de los desertores.\nUna vez que aceptes esta misión, tendrás 5 días para prepararte para el desfile. Considera mejorar tus defensas y elaborar planes de contingencia, ya que es difícil decir en qué dirección se moverá el desfile. En todo momento tendrás que mantener el desfile a salvo de daños.\nVigila a cualquier rival o enemigo de [stellarch_nameFull], ya que podrían decidir que es un buen momento para hacer un movimiento y reclamar el poder para ellos mismos.\nEl transbordador llegará trayendo a la nobleza de más alto rango al desfile. Serás responsable de proporcionar la seguridad para el evento. Después de que comience el desfile, se moverá lentamente por el mapa durante 12 horas, después de lo cual todos, incluido [stellarch_nameFull], abordarán el transbordador y partirán.\n\n\n\n</li>
  </VFEE_Parade.questDescriptionAndNameRules.rulesStrings>
  <!-- EN:
    <li>questName->High Stellarch Ascension</li>
  -->
  <VFEE_Parade.questNameRules.rulesStrings>
    <li>questName->Ascensión del Alto Estelarca</li>
  </VFEE_Parade.questNameRules.rulesStrings>
  
</LanguageData>