<?xml version='1.0' encoding='utf-8'?>
<LanguageData>
  <VFEP_CurseOfAging.description>Los peones envejecen a 10 veces la velocidad.</VFEP_CurseOfAging.description>
  <VFEP_CurseOfAging.label>Maldición del Envejecimiento</VFEP_CurseOfAging.label>
  <VFEP_CurseOfBandana.description>Todo el enfriamiento de armas reducido en un 90%.</VFEP_CurseOfBandana.description>
  <VFEP_CurseOfBandana.label>Maldición del Pañuelo</VFEP_CurseOfBandana.label>
  <VFEP_CurseOfBlind.description>No ves ninguna carta cuando ocurren eventos. Todavía aparecen en la pestaña Historial.</VFEP_CurseOfBlind.description>
  <VFEP_CurseOfBlind.label>Maldición de la Ceguera</VFEP_CurseOfBlind.label>
  <VFEP_CurseOfConfetti.description>Matar a un peón genera una mota de confeti y un sonido de ¡Yupi! de cumpleaños.</VFEP_CurseOfConfetti.description>
  <VFEP_CurseOfConfetti.label>Maldición del Confeti</VFEP_CurseOfConfetti.label>
  <VFEP_CurseOfDarkness.description>Oscuridad intensificada. Cualquier casilla con 0% de luz es completamente negra.</VFEP_CurseOfDarkness.description>
  <VFEP_CurseOfDarkness.label>Maldición de la Oscuridad</VFEP_CurseOfDarkness.label>
  <VFEP_CurseOfFire.description>La lluvia ya no se activa cuando el mapa arde.</VFEP_CurseOfFire.description>
  <VFEP_CurseOfFire.label>Maldición del Fuego</VFEP_CurseOfFire.label>
  <VFEP_CurseOfGluttony.description>El hambre cae al doble de velocidad.</VFEP_CurseOfGluttony.description>
  <VFEP_CurseOfGluttony.label>Maldición de la Gula</VFEP_CurseOfGluttony.label>
  <VFEP_CurseOfGreed.description>Todos los recursos extraíbles rinden oro en lugar de lo que normalmente rendirían.</VFEP_CurseOfGreed.description>
  <VFEP_CurseOfGreed.label>Maldición de la Avaricia</VFEP_CurseOfGreed.label>
  <VFEP_CurseOfInfestation.description>Las infestaciones son el doble de grandes.</VFEP_CurseOfInfestation.description>
  <VFEP_CurseOfInfestation.label>Maldición de la Infestación</VFEP_CurseOfInfestation.label>
  <VFEP_CurseOfInstakill.description>Siempre que un peón fuera derribado, muere.</VFEP_CurseOfInstakill.description>
  <VFEP_CurseOfInstakill.label>Maldición de Muerte Instantánea</VFEP_CurseOfInstakill.label>
  <VFEP_CurseOfMind.description>Todos los efectos de humor se duplican.</VFEP_CurseOfMind.description>
  <VFEP_CurseOfMind.label>Maldición de la Mente</VFEP_CurseOfMind.label>
  <VFEP_CurseOfPestilence.description>La velocidad de ganancia de inmunidad se reduce a la mitad.</VFEP_CurseOfPestilence.description>
  <VFEP_CurseOfPestilence.label>Maldición de la Pestilencia</VFEP_CurseOfPestilence.label>
  <VFEP_CurseOfSteel.description>Todo el daño en el juego se duplica.</VFEP_CurseOfSteel.description>
  <VFEP_CurseOfSteel.label>Maldición del Acero</VFEP_CurseOfSteel.label>
  <VFEP_CurseOfTheArmored.description>Penetración de armas reducida a la mitad.</VFEP_CurseOfTheArmored.description>
  <VFEP_CurseOfTheArmored.label>Maldición del Blindado</VFEP_CurseOfTheArmored.label>
  <VFEP_CurseOfTheBeaten.description>No se pueden atender heridas sin medicina.</VFEP_CurseOfTheBeaten.description>
  <VFEP_CurseOfTheBeaten.label>Maldición del Golpeado</VFEP_CurseOfTheBeaten.label>
  <VFEP_CurseOfTheBoomalopes.description>Cada animal explota al morir.</VFEP_CurseOfTheBoomalopes.description>
  <VFEP_CurseOfTheBoomalopes.label>Maldición de los Boomalopes</VFEP_CurseOfTheBoomalopes.label>
  <VFEP_CurseOfTheEyePatch.description>Precisión a distancia reducida a la mitad.</VFEP_CurseOfTheEyePatch.description>
  <VFEP_CurseOfTheEyePatch.label>Maldición del Parche en el Ojo</VFEP_CurseOfTheEyePatch.label>
  <VFEP_CurseOfTheStabbed.description>Todos los tiempos de reutilización de ataques cuerpo a cuerpo se reducen a la mitad.</VFEP_CurseOfTheStabbed.description>
  <VFEP_CurseOfTheStabbed.label>Maldición del Apuñalado</VFEP_CurseOfTheStabbed.label>
</LanguageData>
